{
  "events": [
    {
      "t": 4.5,
      "kind": "tick",
      "label": "a claim is drawn on real ground"
    },
    {
      "t": 8.5,
      "kind": "lock",
      "label": "it is public, state-owned ground"
    },
    {
      "t": 12.5,
      "kind": "whoosh",
      "label": "the proposal builds onto the empty land, seen fr"
    },
    {
      "t": 16.5,
      "kind": "pulse",
      "label": "the power is enormous and gas-fired"
    },
    {
      "t": 20.5,
      "kind": "riser",
      "label": "scale made legible against something real"
    },
    {
      "t": 24.5,
      "kind": "tick",
      "label": "hard turn to the honest caveat"
    },
    {
      "t": 28.5,
      "kind": "whoosh",
      "label": "the certainty is not real"
    },
    {
      "t": 32.5,
      "kind": "tick",
      "label": "the small, sourced figure"
    },
    {
      "t": 36.0,
      "kind": "boom",
      "label": "a six-times spread, unsettled"
    },
    {
      "t": 39.5,
      "kind": "hit",
      "label": "the demand is unproven"
    },
    {
      "t": 42.5,
      "kind": "whoosh",
      "label": "the human-scale check appears"
    },
    {
      "t": 46.0,
      "kind": "lock",
      "label": "overwhelmingly one-sided"
    },
    {
      "t": 48.5,
      "kind": "hit",
      "label": "the company pushes back on the record, and fails"
    },
    {
      "t": 54.5,
      "kind": "lock",
      "label": "the deadline is live and near"
    },
    {
      "t": 57.5,
      "kind": "boom",
      "label": "the button: the decision is Alaska's"
    }
  ],
  "n": 15
}